{
  "project_info": {
    "project_number": "172317559477",
    "project_id": "dtt-app-1cb75",
    "storage_bucket": "dtt-app-1cb75.appspot.com"
  },
  "client": [
    {
      "client_info": {
        "mobilesdk_app_id": "1:172317559477:android:6fad497a51f5edf5f24cfc",
        "android_client_info": {
          "package_name": "com.example.dtt"
        }
      },
      "oauth_client": [
        {
          "client_id": "172317559477-gri1uvljlioosage7h6tniblrb321haj.apps.googleusercontent.com",
          "client_type": 3
        }
      ],
      "api_key": [
        {
          "current_key": "AIzaSyARoD2pKPbwbs0Y2uVbicw_iWz3uuAMvlk"
        }
      ],
      "services": {
        "appinvite_service": {
          "other_platform_oauth_client": [
            {
              "client_id": "172317559477-gri1uvljlioosage7h6tniblrb321haj.apps.googleusercontent.com",
              "client_type": 3
            }
          ]
        }
      }
    }
  ],
  "configuration_version": "1"
}